[
    {
        "function": "minecraft:set_name",
        "name": {
            "text": "パワーブーストIV",
            "color": "gold",
            "italic": true
        }
    },
    {
        "function": "minecraft:set_lore",
        "lore": [
            {
                "text": "魔法書"
            },
            {
                "text": "cost:60 / cast:100",
                "color": "white"
            },
            {
                "text": "攻撃力を高める",
                "color": "aqua"
            }
        ],
        "replace": true
    }
]